imghash/__init__.py
imghash-0.2.0.dist-info/LICENSE
imghash-0.2.0.dist-info/METADATA
imghash-0.2.0.dist-info/WHEEL
imghash-0.2.0.dist-info/entry_points.txt
imghash-0.2.0.dist-info/RECORD
